odspy/__init__.py
odspy-0.1.0.dist-info/METADATA
odspy-0.1.0.dist-info/WHEEL
odspy-0.1.0.dist-info/top_level.txt
odspy-0.1.0.dist-info/RECORD
