Metadata-Version: 2.4
Name: odspy
Version: 0.1.0
Summary: A library for parsing OpenDocument Spreadsheet (ODS) files.
Home-page: https://github.com/fantastic001/odspy
Author: Stefan Nožinić
Author-email: stefan@lugons.org
Classifier: Programming Language :: Python :: 3
Classifier: License :: OSI Approved :: MIT License
Classifier: Operating System :: OS Independent
Requires-Python: >=3.13
Requires-Dist: lxml
Dynamic: author
Dynamic: author-email
Dynamic: classifier
Dynamic: description
Dynamic: description-content-type
Dynamic: home-page
Dynamic: requires-dist
Dynamic: requires-python
Dynamic: summary
